check-size
setup.py
EFS_Size_Alerter.egg-info/PKG-INFO
EFS_Size_Alerter.egg-info/SOURCES.txt
EFS_Size_Alerter.egg-info/dependency_links.txt
EFS_Size_Alerter.egg-info/requires.txt
EFS_Size_Alerter.egg-info/top_level.txt
alert/__init__.py
alert/mail.py
alert/size.py
efs_size_alerter.egg-info/PKG-INFO
efs_size_alerter.egg-info/SOURCES.txt
efs_size_alerter.egg-info/dependency_links.txt
efs_size_alerter.egg-info/requires.txt
efs_size_alerter.egg-info/top_level.txt