Metadata-Version: 1.0
Name: efs-size-alerter
Version: 0.0.2
Summary: Email User's when their EFS directories exceed a quota
Home-page: https://github.com/fbertsch/efs-size-alerter
Author: Frank Bertsch
Author-email: fbertsch@mozilla.com
License: UNKNOWN
Platform: UNKNOWN
